treads/DT_calculation.py
treads/__init__.py
treads/impeding_delays.py
treads/main.py
treads/recovery_trajectory.py
treads/repair_class.py
treads-1.0.1.dist-info/.DS_Store
treads-1.0.1.dist-info/LICENSE.txt
treads-1.0.1.dist-info/METADATA
treads-1.0.1.dist-info/WHEEL
treads-1.0.1.dist-info/top_level.txt
treads-1.0.1.dist-info/RECORD
