Metadata-Version: 2.1
Name: treads
Version: 1.0.1
Summary: Tool for Recovery Estimation And Downtime Simulation of buildings
Home-page: https://github.com/carlosmolinahutt/treads
Author: Pouria Kourehpaz
Author-email: pouria.kourehpaz@ubc.ca
License: UNKNOWN
Platform: UNKNOWN
Classifier: Programming Language :: Python :: 3
Classifier: License :: OSI Approved :: MIT License
Classifier: Natural Language :: English
Classifier: Operating System :: Microsoft :: Windows
Classifier: Operating System :: MacOS :: MacOS X
Classifier: Operating System :: Unix
Classifier: Programming Language :: Python :: 3.6
Classifier: Programming Language :: Python :: 3.7
Classifier: Topic :: Scientific/Engineering
Requires-Python: >=3.6
